examples/__init__.py
examples/fine_tune.py
vect_gan/__init__.py
vect_gan/checkpoints/pre_trained_vect_gan.pt
vect_gan/synthesizers/__init__.py
vect_gan/synthesizers/base.py
vect_gan/synthesizers/test_vectgan.py
vect_gan/synthesizers/vectgan.py
vect_gan/utils/__init__.py
vect_gan/utils/data_sampler.py
vect_gan/utils/data_transformer.py
vect_gan/utils/test_data_sampler.py
vect_gan/utils/test_data_transformer.py
vect_gan-0.1.1.dist-info/LICENSE
vect_gan-0.1.1.dist-info/METADATA
vect_gan-0.1.1.dist-info/WHEEL
vect_gan-0.1.1.dist-info/top_level.txt
vect_gan-0.1.1.dist-info/RECORD
