Metadata-Version: 2.1
Name: vect-gan
Version: 0.1.1
Summary: A package for generating synthetic molecular tabular data using VECT-GAN.
Home-page: https://github.com/y-babdalla/vect_gan
Author: Youssef Abdalla
Author-email: youssef.abdalla.16@ucl.ac.uk
Classifier: Programming Language :: Python :: 3
Classifier: Operating System :: OS Independent
Requires-Python: >=3.11
License-File: LICENSE
